{
  "/_not-found/page": "app/_not-found/page.js",
  "/api/airtable/route": "app/api/airtable/route.js",
  "/admin/financeiro/page": "app/admin/financeiro/page.js",
  "/page": "app/page.js",
  "/login/page": "app/login/page.js",
  "/teste-supabase/page": "app/teste-supabase/page.js",
  "/(authenticated)/admin/dashboard/page": "app/(authenticated)/admin/dashboard/page.js",
  "/(authenticated)/admin/kanban/page": "app/(authenticated)/admin/kanban/page.js",
  "/(authenticated)/admin/upload/page": "app/(authenticated)/admin/upload/page.js",
  "/(authenticated)/admin/nova-solicitacao/page": "app/(authenticated)/admin/nova-solicitacao/page.js",
  "/(authenticated)/admin/kanban/registros/page": "app/(authenticated)/admin/kanban/registros/page.js",
  "/(authenticated)/admin/produtividade/page": "app/(authenticated)/admin/produtividade/page.js",
  "/(authenticated)/aprovador/pendentes/page": "app/(authenticated)/aprovador/pendentes/page.js",
  "/(authenticated)/op/painel/page": "app/(authenticated)/op/painel/page.js",
  "/(authenticated)/admin/todas-solicitacoes/page": "app/(authenticated)/admin/todas-solicitacoes/page.js",
  "/(authenticated)/gestor/consulta/page": "app/(authenticated)/gestor/consulta/page.js",
  "/(authenticated)/recepcao/todas/page": "app/(authenticated)/recepcao/todas/page.js",
  "/(authenticated)/solicitante/checagens/page": "app/(authenticated)/solicitante/checagens/page.js",
  "/(authenticated)/solicitante/departamento/page": "app/(authenticated)/solicitante/departamento/page.js",
  "/(authenticated)/solicitante/liberacoes/page": "app/(authenticated)/solicitante/liberacoes/page.js",
  "/(authenticated)/solicitante/minhas-solicitacoes/page": "app/(authenticated)/solicitante/minhas-solicitacoes/page.js",
  "/(authenticated)/solicitante/nova-solicitacao/page": "app/(authenticated)/solicitante/nova-solicitacao/page.js",
  "/(authenticated)/suporte/consulta/page": "app/(authenticated)/suporte/consulta/page.js",
  "/(authenticated)/superadmin/painel/page": "app/(authenticated)/superadmin/painel/page.js",
  "/(authenticated)/superadmin/usuarios/page": "app/(authenticated)/superadmin/usuarios/page.js",
  "/(authenticated)/suporte/migracao/page": "app/(authenticated)/suporte/migracao/page.js"
}